SyntheticControlMethods/__init__.py
SyntheticControlMethods/__version__.py
SyntheticControlMethods/main.py
SyntheticControlMethods/optimize.py
SyntheticControlMethods/plot.py
SyntheticControlMethods/tables.py
SyntheticControlMethods/validity_tests.py
SyntheticControlMethods-1.1.16.dist-info/LICENSE
SyntheticControlMethods-1.1.16.dist-info/METADATA
SyntheticControlMethods-1.1.16.dist-info/WHEEL
SyntheticControlMethods-1.1.16.dist-info/top_level.txt
SyntheticControlMethods-1.1.16.dist-info/RECORD
