Metadata-Version: 2.1
Name: SyntheticControlMethods
Version: 1.1.16
Summary: A Python package for causal inference using various Synthetic Control Methods
Home-page: https://github.com/OscarEngelbrektson/SyntheticControlMethods
Author: Oscar Engelbrektson
Author-email: oscar.engelbrektson@gmail.com
License: MIT
Download-URL: https://github.com/OscarEngelbrektson/SyntheticControlMethods
Platform: UNKNOWN
Classifier: Development Status :: 4 - Beta
Classifier: Environment :: Console
Classifier: Intended Audience :: Developers
Classifier: Intended Audience :: Science/Research
Classifier: License :: OSI Approved :: Apache Software License
Classifier: Natural Language :: English
Classifier: Operating System :: Unix
Classifier: Programming Language :: Python :: 3.6
Classifier: Programming Language :: Python :: 3.7
Classifier: Programming Language :: Python :: 3.8
Classifier: Programming Language :: Python
Classifier: Topic :: Scientific/Engineering :: Artificial Intelligence
Requires-Dist: numpy (>=1.17)
Requires-Dist: scipy (==1.4.1)
Requires-Dist: pandas (>=1.1.2)
Requires-Dist: cvxpy (==1.1.7)
Requires-Dist: matplotlib (>=2.2.3)
Requires-Dist: jinja2 (>=2.10)
